heimdall/__init__.py
heimdall/errors.py
heimdall/evaluate.py
heimdall/main.py
heimdall/lib/binaries/libshuffleemail_darwin_amd64
heimdall/lib/binaries/libshuffleemail_darwin_arm64
heimdall/lib/binaries/libshuffleemail_darwin_arm64.h
heimdall/lib/binaries/libshuffleemail_linux_amd64
heimdall/lib/binaries/libshuffleemail_linux_arm64
heimdall/lib/binaries/libshuffleemail_windows_amd64
heimdall/lib/binaries/libshuffleemail_windows_arm64
shuffle_heimdall-0.2.2.dist-info/METADATA
shuffle_heimdall-0.2.2.dist-info/WHEEL
shuffle_heimdall-0.2.2.dist-info/top_level.txt
shuffle_heimdall-0.2.2.dist-info/RECORD
