Metadata-Version: 2.1
Name: shuffle-heimdall
Version: 0.2.2
Summary: An open-source language for email filtering rules.
Author: Aditya
Author-email: aditya@shuffler.io
